simple_job_files-0.2.1.dist-info/licenses/LICENSE
simplejobfiles/__init__.py
simplejobfiles/app.py
simplejobfiles/py.typed
test/__init__.py
test/test_app.py
simple_job_files-0.2.1.dist-info/METADATA
simple_job_files-0.2.1.dist-info/WHEEL
simple_job_files-0.2.1.dist-info/top_level.txt
simple_job_files-0.2.1.dist-info/RECORD
